README.md
setup.py
litesvg/__init__.py
litesvg/litesvg.py
litesvg/mathplus.py
litesvg/transform.py
litesvg.egg-info/PKG-INFO
litesvg.egg-info/SOURCES.txt
litesvg.egg-info/dependency_links.txt
litesvg.egg-info/requires.txt
litesvg.egg-info/top_level.txt