Metadata-Version: 2.1
Name: litesvg
Version: 0.1.0
Summary: This package provides tools to make svg objects (file or in a web page) with rectangles, ellipses, polygons and texts.
Home-page: https://framagit.org/makeforartandscience/litesvg
Author: Make for art and science - Thierry Dassé
License: MIT License
Platform: UNKNOWN
Classifier: Programming Language :: Python :: 3
Classifier: Operating System :: OS Independent
